README.rst
mspdiary.py
setup.py
mspdiary.egg-info/PKG-INFO
mspdiary.egg-info/SOURCES.txt
mspdiary.egg-info/dependency_links.txt
mspdiary.egg-info/entry_points.txt
mspdiary.egg-info/top_level.txt