Metadata-Version: 1.0
Name: mspdiary
Version: 0.0.1
Summary: Daily diary
Home-page: http://github.com/michaelpace/mspdiary/
Author: Michael Pace
Author-email: mpace1027@gmail.com
License: BSD
Keywords: diary
Platform: UNKNOWN
